proxify/__init__.py
proxify/config.py
proxify/handlers/fetch.py
proxify/handlers/storage.py
proxify/handlers/validate.py
proxify/sources/free_proxy_list.py
proxify/sources/geonode.py
proxify/sources/open_proxy_list.py
proxify/sources/proxy_list.py
proxify/sources/proxyscrape.py
proxify/utils/logger.py
proxify/utils/storage.py
proxify_tool-1.0.0.dist-info/licenses/LICENSE
proxify_tool-1.0.0.dist-info/METADATA
proxify_tool-1.0.0.dist-info/WHEEL
proxify_tool-1.0.0.dist-info/top_level.txt
proxify_tool-1.0.0.dist-info/RECORD
