Metadata-Version: 2.4
Name: proxify-tool
Version: 1.0.0
Summary: Proxify is a Python tool for fetching and validating public proxies.
Author: Filming
License: MIT License
Project-URL: Homepage, https://github.com/filming/proxify
Project-URL: Repository, https://github.com/filming/proxify
Requires-Python: >=3.10
License-File: LICENSE
Requires-Dist: aiohttp
Requires-Dist: aiohttp-socks
Requires-Dist: beautifulsoup4
Requires-Dist: lxml
Requires-Dist: Brotli
Requires-Dist: python-dotenv
Dynamic: license-file
